psionapp/__init__.py
psionapp/_version.py
psionapp/applicationbase.py
psionapp/applicationclass.py
psionapp/applicationuser.py
psionapp/config.py
tests/__init__.py
tests/classes_for_testing.py
tests/test_applications.py
tests/test_directories.py
tests/test_user.py
psionapp-0.0.5.dist-info/METADATA
psionapp-0.0.5.dist-info/WHEEL
psionapp-0.0.5.dist-info/top_level.txt
psionapp-0.0.5.dist-info/RECORD
