Metadata-Version: 2.1
Name: psionapp
Version: 0.0.5
Summary: A basic application class which other applications can inherit.
Home-page: https://psionman@bitbucket.org/psionman/psionapp.git
Author: jeff watkins
Author-email: support@bidforgame.com
License: MIT
Download-URL: https://pypi.org/project/psionapp/
Keywords: Application, User, configuration
Platform: UNKNOWN
Requires-Dist: username
Requires-Dist: nose
